colorful_debug/__init__.py
colorful_debug/colorful_debug.py
colorful_debug-1.0.2.dist-info/LICENSE
colorful_debug-1.0.2.dist-info/METADATA
colorful_debug-1.0.2.dist-info/WHEEL
colorful_debug-1.0.2.dist-info/top_level.txt
colorful_debug-1.0.2.dist-info/RECORD
