Metadata-Version: 2.1
Name: colorful-debug
Version: 1.0.2
Summary: A colorful debug print module.
Home-page: UNKNOWN
Author: Nabil El Ouaamari
Author-email: nabil.elouaamari.dev@gmail.com
License: UNKNOWN
Platform: UNKNOWN
License-File: LICENSE
Requires-Dist: termcolor
